setup.py
blockchainauth/__init__.py
blockchainauth/auth_message.py
blockchainauth/auth_request.py
blockchainauth/auth_response.py
blockchainauth/identification.py
blockchainauth/keychain.py
blockchainauth/keys.py
blockchainauth/permissions.py
blockchainauth/resolver.py
blockchainauth/tokenizer.py
blockchainauth/utils.py
blockchainauth.egg-info/PKG-INFO
blockchainauth.egg-info/SOURCES.txt
blockchainauth.egg-info/dependency_links.txt
blockchainauth.egg-info/not-zip-safe
blockchainauth.egg-info/requires.txt
blockchainauth.egg-info/top_level.txt