Metadata-Version: 1.1
Name: blockchainauth
Version: 0.2.0
Summary: Blockchain Auth Library
Home-page: https://github.com/blockstack/blockchain-auth-python
Author: Blockstack Developers
Author-email: hello@onename.com
License: MIT
Keywords: blockchain auth authentication id identity login bitcoin cryptocurrency
Platform: UNKNOWN
Classifier: Intended Audience :: Developers
Classifier: License :: OSI Approved :: MIT License
Classifier: Operating System :: OS Independent
Classifier: Programming Language :: Python
Classifier: Topic :: Internet
Classifier: Topic :: Security :: Cryptography
Classifier: Topic :: Software Development :: Libraries :: Python Modules
